nowfm
