Metadata-Version: 1.1
Name: nowfm
Version: 0.0.21
Summary: nowfm is a library for get nowplaying track information from Last.fm.
Home-page: https://github.com/cloverrose/nowfm
Author: UNKNOWN
Author-email: UNKNOWN
License: UNKNOWN
Keywords: Last.fm library
Platform: UNKNOWN
Classifier: Development Status :: 2 - Pre-Alpha
Classifier: License :: OSI Approved :: Python Software Foundation License
Classifier: Topic :: Software Development :: Libraries
